odoo/addons/account_invoice_partner_reference/README.rst
odoo/addons/account_invoice_partner_reference/__init__.py
odoo/addons/account_invoice_partner_reference/__manifest__.py
odoo/addons/account_invoice_partner_reference/i18n/account_invoice_partner_reference.pot
odoo/addons/account_invoice_partner_reference/i18n/it.po
odoo/addons/account_invoice_partner_reference/models/__init__.py
odoo/addons/account_invoice_partner_reference/models/account_move.py
odoo/addons/account_invoice_partner_reference/readme/CONTRIBUTORS.rst
odoo/addons/account_invoice_partner_reference/readme/DESCRIPTION.rst
odoo/addons/account_invoice_partner_reference/readme/USAGE.rst
odoo/addons/account_invoice_partner_reference/static/description/icon.png
odoo/addons/account_invoice_partner_reference/static/description/index.html
odoo/addons/account_invoice_partner_reference/static/img/readme/partner_reference.png
odoo/addons/account_invoice_partner_reference/static/img/readme/partner_reference_invoice_tree.png
odoo/addons/account_invoice_partner_reference/views/account_move_views.xml
odoo_addon_account_invoice_partner_reference-16.0.1.0.0.4.dist-info/METADATA
odoo_addon_account_invoice_partner_reference-16.0.1.0.0.4.dist-info/WHEEL
odoo_addon_account_invoice_partner_reference-16.0.1.0.0.4.dist-info/top_level.txt
odoo_addon_account_invoice_partner_reference-16.0.1.0.0.4.dist-info/RECORD
